{
	"stage": "stage",
	"events": [],
	"scrollSpeed": 1,
	"codenameChart": true,
	"strumLines": [
		{
			"notes": [],
			"visible": true,
			"strumPos": [
				0,
				50
			],
			"position": "dad",
			"scrollSpeed": null,
			"strumScale": 1,
			"strumLinePos": 0.25,
			"type": 0,
			"characters": [
				"darnell"
			]
		},
		{
			"notes": [],
			"visible": true,
			"strumPos": [
				0,
				50
			],
			"position": "boyfriend",
			"scrollSpeed": null,
			"strumScale": 1,
			"strumLinePos": 0.75,
			"type": 1,
			"characters": [
				"pico"
			]
		},
		{
			"notes": [],
			"visible": false,
			"strumPos": [
				0,
				50
			],
			"position": "girlfriend",
			"scrollSpeed": null,
			"strumScale": 1,
			"strumLinePos": 0.5,
			"type": 2,
			"characters": [
				"nene"
			]
		}
	],
	"meta": null,
	"noteTypes": []
}